scrt/__init__.py
scrt-0.0.1a1.dist-info/METADATA
scrt-0.0.1a1.dist-info/WHEEL
scrt-0.0.1a1.dist-info/top_level.txt
scrt-0.0.1a1.dist-info/RECORD
